{
   "Current password is required":"საჭიროა მიმდინარე პაროლი",
   "Current password must be more than 5 characters":"მიმდინარე პაროლი უნდა იყოს 5 სიმბოლოზე მეტი",
   "New password is required":"საჭიროა ახალი პაროლი",
   "New password must be more than 5 characters":"ახალი პაროლი უნდა იყოს 5 სიმბოლოზე მეტი",
   "Confirmation password is required":"საჭიროა პაროლის დადასტურება",
   "Confirmation password must be more than 5 characters":"პაროლის დასადასტურებლად საჭიროა 5 სიმბოლოზე მეტი",
   "Confirmation password must match":"დადასტურებისას პაროლი უნდა ემთხვეოდეს",
   "Name is required":"აუცილებელია სახელის მითითება",
   "Name must be more than 2 characters":"სახელი უნდა იყოს 2 სიმბოლოზე მეტი",
   "Registration number is required":"აუცილებელია რეგისტრაციის ნომრის მითითება",
   "Registration number must be more than 2 characters":"რეგისტრაციის ნომერი უნდა იყოს 2 სიმბოლოზე მეტი",
   "Country is required":"აუცილებელია ქვეყნის მითითება",
   "Phone is required":"აუცილებელია ტელეფონის ნომრის მითითება",
   "Phone must be more than 6 characters":"ტელეფონის ნომერი უნდა იყოს 6 სიმბოლოზე მეტი",
   "Address is required":"აუცილებელია მისამართის მითითება",
   "Postal code is required":"აუცილებელია საფოსტო ინდექსის მითითება",
   "Postal code must be more than 2 characters":"საფოსტო ინდექსი უნდა იყოს 2 სიმბოლოზე მეტი",
   "E-mail is required":"საჭიროა ელექტრონული ფოსტის მისამართი",
   "E-mail must be valid":"ელექტრონული ფოსტის მისამართი უნდა იყოს მოქმედი",
   "Passport number is required":"საჭიროა პასპორტის ნომრის მითითება",
   "Birth date is required":"აუცილებელია დაბადების თარიღის მითითება",
   "Field is required":"ველი აუცილებლად უნდა იყოს შევსებული",
   "Passport picture is required":"საჭიროა პასპორტის სურათი",
   "Certificate of conviction is required":"საჭიროა ნასამართლეობის ცნობა",
   "Actual address is required":"საჭიროა ფაქტობრივი მისამართი",
   "Legal address is required":"საჭიროა იურიდიული მისამართი",
   "Notification language is required":"საჭიროა შეტყობინების მიღების ენის არჩევა",
   "Registration number must be more than 9 or 11 characters":"რეგისტრაციის ნომერი უნდა იყოს 9 ან 11 სიმბოლოზე მეტი",
   "Valid email is required":"საჭიროა მოქმედი ელექტრონული ფოსტის მისამართი",
   "Password must be more then 5 characters":"პაროლი უნდა იყოს 5 სიმბოლოზე მეტი",
   "You must agree to our privacy policy":"აუცილებელია თქვენი თანხმობა ჩვენს კონფიდენციალურობის პირობებზე",
   "Code must be contain 6 characters":"კოდი უნდა შეიცავდეს 6 სიმბოლოს",
   "Password changed successfully":"პაროლი წარმატებით შეიცვალა",
   "Not uploaded yet":"არ არის ატვირთული",
   "Provider":"გადამზიდი",
   "Client":"კლიენტი",
   "Contact":"კონტაქტი",
   "Get a quote":"პასუხის მიღება მოთხოვნაზე",
   "Verify":"",
   "Cabinet":"კაბინეტი",
   "Sign Up to your Account":"გაიარეთ რეგისტრაცია",
   "Log in to your Account":"გაიარეთ ავტორიზაცია",
   "Forgot password":"დაგავიწყდათ პაროლი",
   "Log in":"შესვლა",
   "Log out":"გამოსვლა",
   "Sign up":"რეგისტრაცია",
   "Privacy policy":"კონფიდენციალურობის პირობები",
   "Email":"ელექტრონული ფოსტა",
   "Phone":"ტელეფონის ნომერი",
   "Address":"მისამართი",
   "Name":"სახელი",
   "Password":"პაროლი",
   "Confirm password":"გაიმეორეთ პაროლი",
   "Recover":"აღდგენა",
   "Current password":"მიმდინარე პაროლი",
   "New password":"ახალი პაროლი",
   "Confirm new password":"დაადასტურეთ ახალი პაროლი",
   "Change":"შეცვლა",
   "Update":"განახლება",
   "Registration number":"რეგისტრაციის ნომერი",
   "Postal code":"საფოსტო ინდექსი",
   "About":"ჩვენს შესახებ",
   "Website":"ვებ. გვერდის მისამართი",
   "Country":"ქვეყანა",
   "Role in company":"როლი კომპანიაში",
   "Personal information":"პერსონალური ინფორმაცია",
   "Company information":"კომპანიის შესახებ",
   "Change password":"პაროლის შეცვლა",
   "Add driver":"მძღოლის დამატება",
   "Submit":"დადასტურება",
   "Passport number":"პასპორტის ნომერი",
   "Passport picture":"პასპორტის სურათი",
   "Certificate of conviction":"ნასამართლეობის ცნობა",
   "Birth date":"დაბადების თარიღი",
   "cancel":"გაუქმება",
   "ok":"დიახ",
   "Drivers":"მძღოლები",
   "Transports":"ტრანსპორტი",
   "Add Transport":"დაამატეთ ტრანსპორტი",
   "Virtual cabinet":"ვირტუალური კაბინეტი",
   "Services":"სერვისები",
   "Dashboard":"საკონტროლო პანელი",
   "Make":"მწარმოებელი",
   "Year of issue":"გამოშვების თარიღი",
   "Trailer number":"გამწევის ნომერი",
   "Truck number":"მისაბმელის ნომერი",
   "Technical passport number":"ტექ.პასპორტის ნომერი",
   "Technical passport issue date":"ტექ. პასპორტის გაცემის თარიღი",
   "Technical passport front picture":"ტექ. პასპორტის წინა გვერდის სურათი",
   "Technical passport back picture":"ტექ.პასპორტის უკანა გვერდის სურათი",
   "Transport front picture":"სატრანსპორტო საშუალების წინა სურათი",
   "Transport back picture":"სატრანსპორტო საშუალების უკანა სურათი",
   "Transport right picture":"სატრანსპორტო საშუალების მარჯვენა სურათი",
   "Transport left picture":"სატრანსპორტო საშუალების მარცხენა სურათი",
   "Additional information (Optional)":"დამატებითი ინფორმაცია (სურვილისამებრ)",
   "Clear":"გასუფთავება",
   "Transport type":"ტრანსპორტის ტიპი",
   "Technical passport information":"ტექ. პასპორტის ინფორმაცია",
   "Transport images":"სატრანსპორტო საშუალების სურათები",
   "Transport possession type":"სატრანსპორტო საშუალების ფლობის ტიპი",
   "Transport possession":"სატრანსპორტო საშუალების მფლობელი",
   "Rent contract (Optional)":"იჯარის ხელშეკრულება (არაა სავალდებულო)",
   "Number":"ნომერი",
   "Type":"ტიპი",
   "Status":"სტატუსი",
   "Edit":"შეცვლა",
   "Active":"აქტიური",
   "Inactive":"არააქტიური",
   "Edit transport":"სატრანსპორტო საშუალების შეცვლა",
   "Edit Documents":"დოკუმენტების შეცვლა",
   "Transport pictures":"სატრანსპორტო საშუალების სურათები",
   "Technical passport pictures":"ტექ.პასპორტის სურათები",
   "Driver":"მძღოლი",
   "Passport pictures":"პასპორტის სურათები",
   "Contract of rent":"იჯარის ხელშეკრულება",
   "Actual address":"ფაქტობრივი მისამართი",
   "Legal address":"იურიდიული მისამართი",
   "Personal number":"პირადი ნომერი",
   "Personal number is required":"აუცილებელია პირადი ნომერი",
   "Notification language":"შეტყობინების ენა",
   "Enter you email":"შეიყვანეთ ელექტრონული ფოსტის მისამართი",
   "We&#39;ve sent you":"ჩვენ გამოგიგზავნეთ",
   "a reset password code":"პაროლის შეცვლა",
   "check your email":"შეამოწმეთ თქვენი ელექტრონული ფოსტა",
   "Next":"შემდეგი",
   "Code":"კოდი",
   "Set a new password":"ახალი პაროლი",
   "Back":"უკან",
   "Password changed":"პაროლი შეიცვალა",
   "successfully":"წარმატებით",
   "Back to main":"მთავარ გვერდზე დაბრუნება",
   "congratulations":"გილოცავთ",
   "registration completed successfully":"რეგისტრაცია წარმატებით დასრულდა",
   "Resend":"ხელახლა გაგზავნა",
   "Further":"მომავალში",
   "Instructions":"ინსტრუქციები",
   "Go back":"უკან დაბრუნება",
   "Something bad happened":"მოხდა რაღაც გაუთვალისწინებელი",
   "Add order":"შეკვეთის დამატება",
   "Initial location":"საწყისი მდებარეობა",
   "Destination":"დანიშნულების ადგილი",
   "Cargo pickup date range":"ტვირთის აღების პერიოდი",
   "From":"დან",
   "To":"მდე",
   "Proceed":"გაგრძელება",
   "km":"კმ",
   "Distance":"მანძილი",
   "Cargo price":"ტვირთის ღირებულება",
   "Cargo weight (kg)":"ტვირთის წონა (კგ)",
   "Enter exact load address zip code":"შეიყვანეთ დატვირთვის ზუსტი მისამართის ZIP კოდი",
   "Enter exact delivery address zip code":"შეიყვანეთ დაცლის ზუსტი მისამართის ZIP კოდი",
   "Enter exact load address":"შეიყვანეთ დატვირთვის ზუსტი მისამართი",
   "Enter exact delivery address":"შეიყვანეთ დაცლის ზუსტი მისამართი",
   "Temperature in celsius":"ტემპერატურა C 0",
   "Calculate rate":"ღირებულების დათვლა",
   "Optional requirements":"დამატებითი მოთხოვნები",
   "Translive price":"Translive-ის ღირებულება",
   "Our calculated price: ":"ჩვენს მიერ დათვლილი ფასი: ",
   "Cargo price invoice (.pdf)":"ტვირთის ინვოისი (.pdf)",
   "Cargo price invoice (.pdf) (Optional)":"Cargo price invoice (.pdf) არასავალდებულო",
   "Your price (Optional)":"თქვენი ფასი (არსავალდებულო)",
   "Place order":"განათავსეთ შეკვეთა",
   "Order details":"შეკვეთის დეტალები",
   "From: ":"საიდან: ",
   "Cargo load address: ":"დატვირთვის მისამართი: ",
   "Cargo load address ZIP code: ":"დატვირთვის მისამართის ZIP კოდი",
   "To: ":"სადამდე: ",
   "Cargo delivery address: ":"ტვირთის დაცლის მისამართი: ",
   "Cargo delivery address ZIP code: ":"დაცლის მისამართის ZIP კოდი: ",
   "Distance: ":"მანძილი: ",
   "Cargo load date interval: ":"ინტერვალი დატვირთვის თარიღებში: ",
   "Cargo price: ":"ტვირთის ღირებულება: ",
   "Cargo weight: ":"ტვირთის წონა: ",
   "Transport type: ":"ტრანსპორტის ტიპი",
   "Additional requirements":"დამატებითი პირობები",
   "Temperature: ":"ტემპერატურა",
   "Account confirmed successfully":"ანგარიში წარმატებით დადასტურდა",
   "You have logged in the system":"თქვენ შეხვედით სისტემაში",
   "You have registered successfully":"თქვენ წარმატებით დარეგისტრირდით",
   "You have logged out the system":"თქვენ გამოხვედით სისტემიდან",
   "Orders":"შეკვეთები",
   "Rate":"ღირებულება",
   "View":"ნახვა",
   "Filter orders":"შეკვეთების გაფილტვრა",
   "Location":"ადგილმდებარეობა",
   "Choose a currency":"აირჩიეთ ვალუტა",
   "Cargo weight":"ტვირთის წონა",
   "kg":"კგ",
   "All":"ყველა",
   "Cargo price invoice: ":"ტვირთის ღირებულების ინვოისი: ",
   "Order":"შეკვეთა",
   "Insurancer: ":"დამზღვევი",
   "not provided":"არ არის გათვალისწინებული",
   "Cargo category":"ტვირთის კატეგორია",
   "Cargo type":"ტვირთის ტიპი",
   "Loading...":"იტვირთება...",
   "No data available":"მონაცემები მიუწვდომელია",
   "ALLOW":"ნებადართულია",
   "NO THANKS":"არა გმადლობთ",
   "Get notified first about your orders, statuses and so much more...":"პირველმა მიიღეთ შეტყობინება თქვენს შეკვეთებზე, სტატუსებზე და ბევრ სხვაზე...",
   "Thank you":"მადლობა",
   "Translive is super excited to have you on board":"Translive მოხარულია გიხილოთ ჩვენს გუნდში",
   "Ok":"დიახ",
   "Profile":"პროფილი",
   "Company":"კომპანია",
   "Settings":"პარამეტრები",
   "Road logistic":"სახმელეთო გადაზიდვები",
   "Send":"გაგზავნა",
   "Recover password":"პაროლის აღდგენა",
   "Congratulations":"გილოცავთ",
   "Newly added driver need to be verified by Translive team in order to use it to make bids on order":"ახალი დამატებული მძღოლი უნდა დადასტურდეს Translive-ის გუნდის მიერ, რომ შეძლოს საიტის გამოყენება და შეკვეთებზე საკუთარი ფასის შეთავაზება",
   "Newly added transport need to be verified by Translive team in order to use it to make bids on order":"ახალი დამატებული ტრანსპორტი უნდა დადასტურდეს Translive-ის გუნდის მიერ, რომ შეძლოს საიტის გამოყენება და შეკვეთებზე საკუთარი ფასის შეთავაზება",
   "GPS Tracking":"GPS ნავიგაცია",
   "IMEI CODE (optional)":"IMEI კოდი (არასავალდებულო)",
   "insurance price included":"დაზღვევის ღირებულება გათვალისწინებულია",
   "pallet":"პალეტი",
   "You have a bid":"თქვენთვის შეთავაზებაა",
   "You have no bid":"თქვენ არ გაქვთ შეთავაზება.",
   "Created at: ":"შექმნილია: ",
   "Bids":"შეთავაზებები ",
   "Only the ones on which I made the bid":"მხოლოდ ის წინადადებები რაზეც განვათავსე შეთავაზება",
   "Accept":"მიღება",
   "Offer new price":"ახალი ფასის შეთავაზება",
   "Make offer":"შეთავაზების გაკეთება",
   "Order price: ":"შეკვეთის ღირებულება: ",
   "About us":"ჩვენს შესახებ",
   "Translive has no previous offers":"Translive-ს არ აქვს შემოთავაზებები",
   "Processing":"დამუშავება",
   "Translive offered you the price:":"Translive-მა შემოგთავაზათ ფასი:",
   "Your previous offer was:":"თქვენი წინა შეთავაზება იყო:",
   "Your current offer is:":"თქვენი მიმდინარე შეთავაზებაა:",
   "Available orders":"ხელმისაწვდომი შეკვეთები",
   "Departure date":"გაგზავის თარიღი",
   "Delivery date":"მიწოდების თარიღი",
   "Price":"ღირებულება",
   "Choose transport":"აირჩიეთ ტრანსპორტი",
   "Choose driver":"აირჩიეთ მძღოლი",
   "Place bid":"ფასის შეთავაზება",
   "Additional information":"დამატებითი ინფორმაცია",
   "Maximum price you can offer is:":"მაქსიმალური ფასი რისი შეთავაზებაც შეგიძლიათ არის:",
   "Price must be less then":"ფასი ნაკლები უნდა იყოს ვიდრე",
   "Update price":"ფასის განახლება",
   "Update bid":"განაახლე ფასი",
   "Your price for this order is":"თქვენი ფასი ამ შეთავაზებისთვის არის",
   "Transport":"ტრანსპორტი ",
   "Expected departure date":"გაგზავნის მოსალოდნელი თარიღი",
   "Expected delivery date":"მიწოდების მოსალოდნელი თარიღი",
   "Follow":"მიყოლა",
   "link":"ლინკი ",
   "to add drivers":"მძღოლების დასამატებლად",
   "to add transports":"ტრანსპორტის დასამატებლად",
   "for more information":"დამატებითი ინფორმაციისთვის",
   "Contact us":"დაგვიკავშირდით",
   "Order document":"შეკვეთის დოკუმენტი",
   "Signed order documet":"ხელმოწერილი შეკვეთის დოკუმენტი",
   "Upload":"ატვირთვა",
   "Download template":"შაბლონის ჩამოტვირთვა",
   "Price for this order is":"მოცემული შეკვეთის ფასი არის",
   "Not provided":"არ არის გათვალისწინებული",
   "Reupload signed order documet":"ხელმოწერილი შეკვეთის დოკუმენტის ხელახლა ატვირთვა",
   "update cargo price invoice":"განაახლე ტვირთის ინვოისი",
   "View uploaded signed order document":"ატვირთული ხელმოწერილი შეკვეთის დოკუმენტის ნახვა",
   "My orders":"ჩემი შეკვეთები",
   "Signed order document":"ხელმოწერილი შეკვეთის დოკუმენტი",
   "Order invoice":"შეკვეთის ინვოისი",
   "CMR document":"CMR დოკუმენტი",
   "Offer is acceptable":"შეთავაზება მისაღებია",
   "Upload CMR after arriving at the destination":"CMR დოკუმენტის ატვირთვა დანიშნულების ადგილზე მისვლის შემდგომ",
   "Your offer on this order has been confirmed":"თქვენი შეთავაზება აღნიშნულ შეკვეთაზე დადასტურებულია.",
   "View uploaded CMR":"ატვირთული CMR-ის ნახვა",
   "Order is on it's way to destination":"შეკვეთა იგზავნება ადრესატთნ",
   "Order is delivered and waiting for CMR":"შეკვეთა მიწოდებულია და ელოდება CMR-ს",
   "Order is completed succesfully":"შეკვეთა დასრულდა წარმატებით",
   "Order is failed. There were some problems and shipping wasn't successfull":"შეკვეთა წარუმატებელია. წარმოიშვა რამოდენიმე პრობლემა და დატვირთვა ვერ განხორციელდა",
   "Reupload CMR document":"» CMR დოკუმენტის ხელახლა ატვირთვა",
   "Documents are ready and order is waiting for cargo to be loaded":"დოკუმენტები მზადაა და შეკვეთის მიხედვით  ელოდებიან ტვირთის დატვირთვას",
   "Order is confirmed and is waiting for possible carrier":"შეკვეთა დადასტურებულია და ელოდება შესაბამის გადამზიდავს",
   "Download your order document below, sign it and upload whenever possible":"ჩამოტვირთეთ შეკვეთის განაცხადი და შეძლებისამებრ ატვირთეთ ხელმოწერილი",
   "Carrier is found for this order. Order is waiting for documents to get ready":"მოცემული შეკვეთისთვის ნაპოვნია გადამზიდი. შეკვეთის მზაობისთვის საჭიროა შესაბამისი დოკუმენტები",
   "Order is under negotiation between you and  Translive admin. You have two options, accept admin's price or offer your own one":"შეკვეთა განხილვის პროცესშია თქვენსა და Translive-ის ადმინისტრატორს შორის. თქვენ გაქვთ ორი ვარიანტი დათნხმდეთ ადმინისტრატორის ფასს ან შემოგვთავაზოთ თქვენი",
   "Order is in the process of review and will be confirmed shortly by the Translive administrator in the absence of certain problems":"შეკვეთა განხილვის პროცესშია Translive-ის ადმინისტრატორის მიერ და უმოკლეს ვადაში დადასტურდება თუ არ იარსებებს გარკვეული პრობლემები",
   "In order to make bids on orders, you need drivers and transports, wich are verified by Translive team":"შეკვეთებზე ფასების განსათავსებლად თქვენ გჭირდებათ Translive-ის გუნდის მიერ შემოწმებული მძღოლები და ტრანსპორტი",
   "Here is your personal details provided by you. You can edit them as per your requirements any time you want. Soon, we'll add more details for you to fill in so that your experience gets much more elegant.":"აქ მოცემულია თქვენი პერსონალური მონაცემები. მათი ცვლილება შესაძლებელია თქვენი მოთხოვნის შესაბამისად. დამატებითი დეტალები დაემატება  შესაბამისი მოთხოვნის მიხედვით",
   "Here is your company details provided by you. You can edit them as per your requirements any time you want. Soon, we'll add more details for you to fill in so that your experience gets much more elegant.":"აქ მოცემულია თქვენი პერსონალური მონაცემები. მათი ცვლილება შესაძლებელია თქვენი მოთხოვნის შესაბამისად. დამატებითი დეტალები შესავსებად დაემატება  შესაბამისი მოთხოვნის მიხედვით",
   "The cost for this order is calculated depending on your order type, cargo type, cargo price and distance. Keep in mind that it also includes the insurance price. The currency that you pay in depends on the currency your document possesses for your cargo price. For example: If you upload a document that states that your cargo price is evaluated in USD, even though the currencies of the countries your cargo might cross might vary, you'll still pay in USD. So the currency you pay in will be the same as the currency that is shown on your cargo price document.":"შეკვეთის ღირებულება განისაზღვრება საჭირო ტრანსპორტის, ტვირთის ტიპის, ტვირთის ღირებულების და მანძილის მიხედვით. ღირებულება შეიძლება შეიცავდეს დაზღვევის ხარჯებს. ვალუტა, რომელსაც გადაიხდით განისაზღვრება იმით, თუ რომელ ვალუტაშია მოცემული თქვენი ტვირთის ღირებულება. მაგალითად: თუ თქვენ ატვირთავთ დოკუმენტს, სადაც ტვირთის ვალუტა იქნება ამერიკული დოლარი, თუნდაც ტვირთის ტრანსპორტირება განხორციელდეს იმ ქვეყნების გავლით სადაც ვალუტა განსხვავდება ამერიკული დოლარისგან, თქვენ მაინც გადაიხდით ამერიკულ დოლარს. აქედან გამომდინარე, თქვენს მიერ გადახდილი ვალუტა, ტვირთის დოკუმენტში მითითებულ ვალუტის იდენტური იქნება",
   "The best thing about Translive is that you have a possibility of bargaining about the order price we calculated. You can make bids stating that you'd only want this order if our calculated price would be 10% less.  This way, Translive and you will be trading and finding the best price possible for both sides. Keep in mind that until both of the parties(Translive and you) agree on the actual price, your orders won't get started.":"Translive-ის უპირატესობა მდგომარეობს იმაში, რომ თქვენ გაქვთ საშუალება აწარმოოთ მოლაპარაკება შეკვეთის ფასზე, რომელიც ჩვენ დავთვალეთ. თქვენ შეგიძლიათ გააკეთოთ შეთავაზება, სადაც ნათქვამია, რომ გსურთ  ეს შეკვეთა მხოლოდ იმ შემთხვევაში, თუ ჩვენი გამოთვლილი ფასი 10% -ით ნაკლები იქნება. შესაბამისად, Translive  და თქვენ აწარმოებთ მოლაპარაკებებს და შეთანხმდებით საუკეთესო ფასზე, რომელიც დააკმაყოფილებს ორივე მხარეს. გაითვალისწინეთ, რომ სანამ ორივე მხარე (Translive და თქვენ) არ შეთანხმდებით რეალურ ფასზე თქვენი შეკვეთა არ დაიწყება",
   "Each of your order goes through different kind of process(when it's unconfirmed, confirmed, pending, released and so many more). To make it simpler for you to understand what step it is at, beside each order, There's a status field upon which there'll be shown some explanations when hovering your mouse on it. It's important to know what step an order is through, because depending on the status, we send different kind of notifications, smses, emails and so much more.":"ყოველი თქვენი შეკვეთა გადის სხვადასხვა ეტაპს (როდესაც არ არის დადასტურებული, დადასტურებულია, იგზავნება, გაგზავნილია და ა.შ). იმისათვის, რომ ადვილი იყოს გაგება თუ რომელ ეტაპზეა, ყველა შეკვეთას აქვს შესაბამისი სტატუსი, რომლის ახსნაც ნაჩვენები იქნება მასზე „მაუსის“ მიტანისას. აუცილებელია იმის ცოდნა თუ რომელ ეტაპზეა თქვენი შეკვეთა, ვინაიდან სტატუსის შესაბამისად ჩვენ ვაგზავნით სხვადასხვა სახის შეტყობინებებს სმს-ის, ელექტრონული ფოსტის და ბევრი სხვა პროგრამის დახმარებით.",
   "Translive is happy to announce that we can transport your cargo if its type is shown when you choose cargo type field at the left side. If it's not shown, you can choose 'other' kind and type the cargo name in your words. Keep in mind that, if this is the case, as for now, your order won't be added on our platform, but we'll still contact you and make it happen by using other methods.":"Translive-მოხარულია გაცნობოთ, რომ ჩვენ შეგვიძლია მოვახდინოთ თქვენი ტვირთის ტრანსპორტირება, თუ მისი ტიპი აღნიშნულია მარცხენა მხარეს არსებულ ტვირთის ტიპების ჩამონათვალში. თუ მოთხოვნილი ტიპი არ არის ჩამონათვალში, თქვენ შეგიძლიათ აირჩიოთ „სხვა“ და შეიყვანოთ ტვირთის დასახელება თქვენი სიტყვებით. გახსოვდეთ, რომ ასეთ შემთხვევაში თქვენი შეკვეთა არ იქნება დამატებული ჩვენს პლატფორმაზე, თუმცა ჩვენ დაგიკავშირდებით და გავაკეთებთ ყველაფერს, რომ თქვენ შეძლოთ შეკვეთის დამატება", 
   "Cargo price invoice is the official document which states at how much price cargo is approximatelly assessed. Please, keep in mind that for better understanding and quicker results, you MUST choose the currency that is the same as the price for your cargo is shown on cargo price invoice document.  The currency you choose(which must be the same as your cargo price invoce document) will be the one you'll pay your cost in.":"ტვირთის ღირებულების ინვოისი არის ოფიციალური დოკუმენტი, რომელიც განსაზღვრავს ტვირთის ღირებულებას. გთხოვთ გაითვალისწინოთ, რომ სწრაფი და უკეთესი შედეგისთვის თქვენ უნდა აირჩიოთ ვალუტა, რომელიც ემთხვევა თქვენი ტვირთის საინვოისო ღირებულებას. თქვენს მიერ არჩეული ვალუტა (რომელიც უნდა ემთხვეოდეს ტვირთის ინვოისში მოცემული ფასის ვალუტას) იქნება ის რომლის მიხედვითაც თქვენს გადაიხდით ყველა  ხარჯს",
   "In order to provide tracking for truck, you should provide IMEI code of truck's GPS device when adding the concrete transport. Otherwise tracking will occur for drivers by the application's GPS service on driver's smartphone.":"იმისთვის, რომ უზრუნველვჰყოთ სატრანსპორტო საშუალების ადგილმდებარეობის განსაზღვრა, თქვენ უნდა წარმოადგინოთ სატრანსპორტო საშუალების GPS-ს მოწყობილობის IMEI კოდი კონკრეტული ტრანსპორტის დამატების დროს. წინააღმდეგ შემთხვევაში ადგილმდებარეობის განსაზღვრა იწარმოებს მძღოლების სმარტფონებში არსებული GPS პროგრამის მეშვეობით",
   "ABOUT US":"ჩვენს შესახებ",
   "WELCOME TO TRANSLIVE LOGISTIC":"WELCOME TO TRANSLIVE LOGISTIC",
   "Translive is a smart digital transportation management system for all carriers and shippers, which makes logistics much more efficient and improves your profitability. Our marketplace connects them using data to match freight with capacity, pairing the right load with the right carrier on the requested route and guarantees you cost savings":"Translive არის ციფრული ტრანსპორტირების მართვის გონივრული სისტემა, ნებისმიერი სახის ტვირთის გადაზიდვის და გაგზავნისთვის, რომელიც ლოგისტიკურ საქმიანობას ბევრად უფრო ეფექტურს ხდის და აუმჯობესებს თქვენს შემოსავალს. მონაცემების გამოყენების საშუალებით, ჩვენი ბაზა ერთმანეთთან აკავშირებს გადამზიდავს და გამგზავნს, რომ მოთხოვნილ მარშრუტზე , ტვირთი შეუსაბამოს ტევადობას და გადამზიდის მოთხოვნას, რაც იძლევა თქვენი ხარჯების შემცირების გარანტიას.",
   "Digital Freight Marketplace":"ციფრული ტვირთის ბაზარი",
   "Shippers can quote, book, and ship freight online and carriers can search thousands of available loads, make offers on freight in their favorite lanes, and dispatch drivers":" გამგზავნებს შესაძლებლობა აქვთ დაადგინონ ტარიფი, დაჯავშნონ და გაგზავნონ ტვირთი ონლაინ რეჟიმში. გადამზიდავებს შესაძლებლობა ეძლევათ მოიძიონ მრავალი ხელმისაწვდომი ტვირთი. მათთვის სასურველი მარშრუტით გააკეთონ შეთავაზებები და გაგზავნონ მძღოლები",
   "Supply Chain Insights":"მიწოდების ჯაჭვის არსი",
   "You’ll enjoy quick access to business critical information in an easy-to-use interface. Identify efficiencies and make smart business decisions":"მარტივად გამოსაყენებელი ინტერფეისის მეშვეობით, თქვენ ისარგებლებთ ბიზნესისთვის მნიშვნელოვანი ინფორმაციით. განსაზღვრავთ ეფექტურობას და მიიღებთ გონივრულ საქმიან გადაწყვეტილებებს.",
   "Exceptional Experience":"უნიკალური გამოცდილება",
   "Platform unites only high standard logistic companies and provides continuous freight control. It Suggests flexible tariff system, insurance and easy documentation filling process. Translive creates reliable logistic space, staffed by professional members, with many years of experience":"პლატფორმა აერთიანებს მხოლოდ მაღალი სტანდარტის მქონე ლოგისტიკურ კომპანიებს და უზრუნველჰყოფს ტვირთის უწყვეტ კონტროლს. პლატფორმა გვთავაზობს მოქნილ სატარიფო სისტემას, დაზღვევას და დოკუმენტაციის შევსების გამარტივებულ პროცესს. Translive ქმნის სანდო ლოგისტიკურ სივრცეს, რომელიც დაკომპლექტებულია მრავალწლიანი გამოცდილების მქონე პროფესიონალებით",
   "Are You A Carrier?":"ხართ გადამზიდველი?",
   "Streamline operations with end-to-end load management.":"გამარტივებული ოპერაციები ტვირთის მენეჯმენტის პროცესის დასაწყისიდან ბოლომდე.",
   "Log in once to find, book and accept loads.":"გაიარეთ ავტორიზაცია ერთხელ, რომ იპოვოთ, დაჯავშნოთ და მიიღოთ ტვირთები",
   "Are You A Shipper?":"ხართ გამგზავნი?",
   "A full service platform with full visibility into your supply chain. Access one of the largest transportation system for creating shipments quickly, receive alerts, offer status, and load updates.":"სრული მომსახურების პლატფორმა თქვენი მიწოდების ჯაჭვის სრული ხილვადობით. მიმართეთ ერთ-ერთ უდიდეს სატრანსპორტო სისტემას სწრაფი გადაზიდვების განსახორციელებლად",
   "Check Now":"განაგრძე",
   "shipments":"გადაზიდვა",
   "in one space":"ერთ სივრცეში",
   "We are committed to be the leading":"ჩვენ მზად ვართ ვიყოთ წამყვანი",
   "TRACK YOUR ORDER":"თვალი ადევნეთ შეკვეთას",
   "ENTER YOUR TRACK ID FOR INSTANT SEARCH":"შეიყვანეთ თქვენი შეკვეთის იდენტიფიკატორი",
   "Completed":"დასრულებული",
   "Failed":"გაფუჭებული",
   "In delivery":"გზაშია",
   "Your orders statistic":"შეკვეთების სტატისტიკა",
   "FEATURE":"მახასიათებელი",
   "Our Featured And Skills":"განსაკუთრებული მახასიათებელი",
   "Verified carriers":"დადასტურებელი გადამზიდავები",
   "To ensure customer service levels are met":"რომ უზრუნველჰყოფილ იქნეს  მომხმარებლის მომსახურების სათანადო დონე",
   "Smartness":"გონივრულობა",
   "Creating shipments quickly from quotes or based on previous loads or shipments.":"გადაზიდვების სწრაფად განხორციელება ტარიფის დადგენით ან წინა ტვირთების თუ გადაზიდვების საფუძველზე.",
   "Tracking Non-Stop":"თვალყურის დევნა უწყვეტ რეჟიმში",
   "Online order’s shipping status is always within reach":"ონლაინ შეკვეთის გადაზიდვის სტატუსი ყოველთვის ხელმისაწვდომია",
   "Insurance":"დაზღვევა",
   "Every load is insured and protected.":"ყველა ტვირთი დაზღვეული და დაცულია.",
   "Documentation":"დოკუმენტაცია",
   "Easy online documentation system":"გამარტივებული ონლაინ დოკუმენტაციის სისტემა",
   "Now Available On":"ამჟამად ხელმისაწვდომია",
   "Application is now available on iOS and Android* - Gives you one continuous logistic experience for your mobile device":"აპლიკაცია ამჟამად ხელმისაწვდომია iOS-სა და Android*-ზე - უზრუნველჰყოფს ერთიან უწყვეტ ლოგისტიკურ გამოცდილებას თქვენი მობილური მოწყობილობისთვის",
   "Text":"ტექსტი",
   "Send us an Email":"გამოგვიგზავნეთ შეტყობინება",
   "Coming soon":"ძალიან მალე",
   "For more information":"მეტი ინფორმაციისთვის",
   "Bussiness Hours":"სამუშაო საათები",
   "Monday":"ორშაბათი",
   "Friday":"პარასკევი",
   "Saturday":"შაბათი",
   "Sunday":"კვირა",
   "Closed":"დაკეტილი",
   "Links":"ბმულები",
   "Add transport":"ტრანსპორტის დამატება",
   "No information":"ინფორმაცია ხელმიუწვდომელია",
   "Administrator":"ადმინისტრატორი",
   "Search":"ძებნა",
   "Not assigned yet":"ჯერ არ არის დანიშნული",
   "Full name":"სრული სახელი",
   "Rating":"რეიტინგი",
   "Rated by":"შეფასებულია",
   "times":"ჯერ",
   "Public Registry Extract":"საჯარო რეესტრის ამონაწერი",
   "Please provide the registration number of company":"გთხოვთ შეიყვანოთ კომპანიის სარეგისტრაციო ნომერი",
   "The company is not registered with this registration number":"კომპანია სარეგისტრაციო ნომრით",
   "If you want to add the company with the registration number":"თუ თქვენ გსურთ დაამატოთ კომპანია მითითებული სარეგისტრაციო ნომრით",
   "please fill out the form":"გთხოვთ შეავსოთ ფორმა",
   "Company name":"კომპანიის სახელი",
   "The company with the registration number":"კომპანია სარეგისტრაციო ნომრით",
   "is already registered, if you are from the same company please provide the unique code, which we gave to this company":"უკვე დარეგისტრირებულია, თუ თქვენ ხართ ამ კომპანიის წარმომადგენელი გთხოვთ მოგვაწოდოთ უნიკალური კოდი რომელიც მივანიჭეთ ამ კომპანიას",
   "Company unique code":"კომპანიის უნიკალური კოდი",
   "Continue":"გაგრძელება",
   "Documents":"დოკუმენტები",
   "Upload document":"ატვირთეთ დოკუმენტი",
   "File":"ფაილი",
   "Uploaded documents":"ატვირთული დოკუმენტები",
   "unique code":"უნიკალური კოდი",
   "Rate and Review Our Provider Service":"მიმოიხილეთ და შეაფასეთ ჩვენი სერვისის მომწოდებელი",
   "Rate and Review driver":"მიმოიხილეთ და შეაფასეთ მძღოლი",
   "Optional":"სურვილისამებრ",
   "Review":"მიმოხილვა",
   "General promotion":"გენერალური ხელშეკრულება",
   "Please download the template, sign it and upload":"გადმოწერეთ შაბლონი, მოაწერეთ ხელი და ატვირთეთ",
   "The template is always available":"შაბლონი ყოველთვის ხელმისაწვდომია",
   "Cargo load interval":"დატვირთვის ინტერვალი",
   "Select the countries you will pass":"მონიშნეთ ქვეყნები რომლებსაც გაივლით",
   "Countries to pass":"გასავლელი ქვეყნები",
   "Show":"ნახვა",
   "Upload cargo invoice":"ტვირთის ინვოისის ატვირთვა"
}